spanalyzer/__init__.py
spanalyzer/cli.py
spanalyzer/constants/__init__.py
spanalyzer/constants/exceptions.py
spanalyzer/constants/telemetry.py
spanalyzer/engine.py
spanalyzer/java/__init__.py
spanalyzer/java/constants/__init__.py
spanalyzer/java/constants/keywords.py
spanalyzer/java/detector.py
spanalyzer/java/hunters.py
spanalyzer/java/script.py
spanalyzer/python/__init__.py
spanalyzer/python/constants/__init__.py
spanalyzer/python/constants/keywords.py
spanalyzer/python/detector.py
spanalyzer/python/hunters.py
spanalyzer/python/script.py
spanalyzer/reports.py
spanalyzer/utils/__init__.py
spanalyzer/utils/operations.py
spanalyzer-1.0.4.dist-info/entry_points.txt
spanalyzer-1.0.4.dist-info/WHEEL
spanalyzer-1.0.4.dist-info/METADATA
spanalyzer-1.0.4.dist-info/RECORD
