Metadata-Version: 2.1
Name: spanalyzer
Version: 1.0.4
Summary: A tool to analyze telemetry implementation in codebases
Author: Joao Nisa
Author-email: joao.je.nisa@gmail.com
Requires-Python: >=3.10,<4.0
Classifier: Programming Language :: Python :: 3
Classifier: Programming Language :: Python :: 3.10
Classifier: Programming Language :: Python :: 3.11
